<?xml version="1.0" encoding="utf-8"?>
<!DOCTYPE hibernate-mapping PUBLIC "-//Hibernate/Hibernate Mapping DTD 3.0//EN"
"http://www.hibernate.org/dtd/hibernate-mapping-3.0.dtd">
<!-- 
    Mapping file autogenerated by MyEclipse Persistence Tools
-->
<hibernate-mapping>
    <class name="com.owmax.model.Blanks" table="blanks" catalog="owmax">
        <id name="id" type="java.lang.Integer">
            <column name="id" />
            <generator class="identity" />
        </id>
        <many-to-one name="questions" class="com.owmax.model.Questions" fetch="select">
            <column name="question_id" not-null="true" />
        </many-to-one>
        <property name="blankText" type="java.lang.String">
            <column name="blank_text">
                <comment>当为多项填空时为填空单项文字，否则为空</comment>
            </column>
        </property>
        <set name="answerBlankses" inverse="true">
            <key>
                <column name="blank_id" />
            </key>
            <one-to-many class="com.owmax.model.AnswerBlanks" />
        </set>
    </class>
</hibernate-mapping>
